imbue_core/__init__.py
imbue_core/async_future_queue.py
imbue_core/async_monkey_patches.py
imbue_core/async_utils.py
imbue_core/async_utils_test.py
imbue_core/cattrs_serialization.py
imbue_core/cattrs_serialization_test.py
imbue_core/clean_tasks.py
imbue_core/common.py
imbue_core/conftest.py
imbue_core/constants.py
imbue_core/debug_utils.py
imbue_core/error_utils.py
imbue_core/errors.py
imbue_core/fixed_traceback.py
imbue_core/fixtures.py
imbue_core/frozen_utils.py
imbue_core/frozen_utils_test.py
imbue_core/git.py
imbue_core/git_data_types.py
imbue_core/git_snapshot.py
imbue_core/git_test.py
imbue_core/gitlab_management.py
imbue_core/itertools.py
imbue_core/language_model_mode.py
imbue_core/local_sync.py
imbue_core/log_utils.py
imbue_core/nested_evolver.py
imbue_core/py.typed
imbue_core/pydantic_serialization.py
imbue_core/pydantic_serialization_test.py
imbue_core/pydantic_utils.py
imbue_core/pydantic_utils_test.py
imbue_core/queue.py
imbue_core/repo_state.py
imbue_core/repo_state_utils.py
imbue_core/retry_utils.py
imbue_core/secrets_utils.py
imbue_core/section.py
imbue_core/sentry_loguru_handler.py
imbue_core/serialization.py
imbue_core/serialization_types.py
imbue_core/test_errors.py
imbue_core/testing_utils.py
imbue_core/time_utils.py
imbue_core/computing_environment/__init__.py
imbue_core/computing_environment/computing_environment.py
imbue_core/computing_environment/data_types.py
imbue_core-0.0.10.dist-info/licenses/LICENSE
imbue_core-0.0.10.dist-info/METADATA
imbue_core-0.0.10.dist-info/WHEEL
imbue_core-0.0.10.dist-info/top_level.txt
imbue_core-0.0.10.dist-info/RECORD
