Metadata-Version: 2.4
Name: imbue-core
Version: 0.0.10
Summary: Utilities for imbue-desktop.
Author-email: Imbue <imbue@imbue.com>
License-Expression: MIT
Project-URL: homepage, https://imbue.com/
Requires-Python: <3.13,>=3.11
License-File: LICENSE
Requires-Dist: anyio
Requires-Dist: attrs
Requires-Dist: cachetools
Requires-Dist: cattrs
Requires-Dist: httpx
Requires-Dist: inline-snapshot
Requires-Dist: loguru
Requires-Dist: pathspec
Requires-Dist: pydantic>=2.11.4
Requires-Dist: pydantic-settings
Requires-Dist: pyhumps
Requires-Dist: pytest
Requires-Dist: pytest-asyncio
Requires-Dist: pytest-mock
Requires-Dist: tblib==2.0.0
Requires-Dist: traceback-with-variables>=2.2.0
Requires-Dist: yasoo
Requires-Dist: sentry-sdk
Requires-Dist: tenacity>=8.2.2
Requires-Dist: grpclib>=0.4.7
Dynamic: license-file
